pyInjection/__init__.py
pyInjection/py.typed
pyInjection/container/__init__.py
pyInjection/container/container.py
pyInjection/container/container_instance.py
pyInjection/dtos/__init__.py
pyInjection/dtos/registration.py
pyInjection/dtos/signature_parameter.py
pyInjection/enums/__init__.py
pyInjection/enums/scope.py
pyInjection/helpers/__init__.py
pyInjection/helpers/container_helpers.py
pyInjection/helpers/type_helpers.py
pyInjection/interfaces/__init__.py
pyInjection/interfaces/iscope_manager.py
pyInjection/interfaces/ivalidator.py
pyInjection/scope_managers/__init__.py
pyInjection/scope_managers/singleton_scope_manager.py
pyInjection/scope_managers/transient_scope_manager.py
pyInjection/validators/__init__.py
pyInjection/validators/decorator_validator.py
pyInjection/validators/primitive_dependency_validator.py
pyinjection-2.2.dist-info/METADATA
pyinjection-2.2.dist-info/WHEEL
pyinjection-2.2.dist-info/top_level.txt
pyinjection-2.2.dist-info/RECORD
