Metadata-Version: 2.4
Name: pyInjection
Version: 2.2
Summary: Dependency injection container for Python3
Author-email: Joshua Loader <pyInjection@joshloader.com>
License: MIT License
Keywords: dependency injection,Python3,utilities
Classifier: Programming Language :: Python :: 3
Classifier: License :: OSI Approved :: MIT License
Classifier: Operating System :: OS Independent
Requires-Python: >=3.12
Requires-Dist: attrs~=25.1
